promonet/__init__.py
promonet/convert.py
promonet/load.py
promonet/adapt/__init__.py
promonet/adapt/__main__.py
promonet/adapt/core.py
promonet/assets/augmentations/daps-loudness.json
promonet/assets/augmentations/daps-pitch.json
promonet/assets/augmentations/libritts-loudness.json
promonet/assets/augmentations/libritts-pitch.json
promonet/assets/augmentations/vctk-loudness.json
promonet/assets/augmentations/vctk-pitch.json
promonet/assets/configs/reconstruction-quality-mushra.yaml
promonet/assets/configs/reconstruction-similarity-abx.yaml
promonet/assets/configs/shifting-quality-mushra.yaml
promonet/assets/configs/stretching-quality-mushra.yaml
promonet/assets/partitions/adaptation/daps.json
promonet/assets/partitions/adaptation/libritts.json
promonet/assets/partitions/adaptation/vctk.json
promonet/assets/partitions/multispeaker/daps.json
promonet/assets/partitions/multispeaker/vctk.json
promonet/assets/stats/vctk-256-loudness-pitch-viterbi.pt
promonet/assets/stats/vctk-256-loudness-pitch.pt
promonet/assets/stats/vctk-256-viterbi.pt
promonet/assets/stats/vctk-train-speaker-averages-viterbi.json
promonet/baseline/__init__.py
promonet/baseline/mels.py
promonet/baseline/world.py
promonet/config/__init__.py
promonet/config/defaults.py
promonet/config/static.py
promonet/data/__init__.py
promonet/data/collate.py
promonet/data/dataset.py
promonet/data/loader.py
promonet/data/sampler.py
promonet/data/augment/__init__.py
promonet/data/augment/__main__.py
promonet/data/augment/core.py
promonet/data/augment/loudness.py
promonet/data/augment/pitch.py
promonet/data/download/__init__.py
promonet/data/download/__main__.py
promonet/data/download/core.py
promonet/data/pack/__init__.py
promonet/data/pack/__main__.py
promonet/data/pack/core.py
promonet/data/preprocess/__init__.py
promonet/data/preprocess/__main__.py
promonet/data/preprocess/core.py
promonet/edit/__init__.py
promonet/edit/__main__.py
promonet/edit/core.py
promonet/edit/grid.py
promonet/evaluate/__init__.py
promonet-0.0.1.dist-info/LICENSE
promonet-0.0.1.dist-info/METADATA
promonet-0.0.1.dist-info/WHEEL
promonet-0.0.1.dist-info/top_level.txt
promonet-0.0.1.dist-info/RECORD
