Metadata-Version: 2.1
Name: promonet
Version: 0.0.1
Summary: Prosody Modification Network
Home-page: https://github.com/maxrmorrison/promonet
Author: Interactive Audio Lab
Author-email: interactiveaudiolab@gmail.com
License: MIT
Keywords: speech,prosody,editing,synthesis,pronunciation
License-File: LICENSE
Requires-Dist: GPUtil
Requires-Dist: huggingface-hub
Requires-Dist: jiwer
Requires-Dist: librosa
Requires-Dist: matplotlib
Requires-Dist: numpy
Requires-Dist: openai-whisper
Requires-Dist: penn
Requires-Dist: ppgs
Requires-Dist: pypar
Requires-Dist: pyworld
Requires-Dist: resampy
Requires-Dist: scipy
Requires-Dist: soundfile
Requires-Dist: transformers
Requires-Dist: torch
Requires-Dist: torchaudio
Requires-Dist: torchutil
Requires-Dist: umap-learn
Requires-Dist: vocos[train]
Requires-Dist: yapecs
